pip_search_two/__init__.py
pip_search_two/main.py
pip_search_two-1.1.0.dist-info/licenses/LICENSE
pip_search_two-1.1.0.dist-info/METADATA
pip_search_two-1.1.0.dist-info/WHEEL
pip_search_two-1.1.0.dist-info/entry_points.txt
pip_search_two-1.1.0.dist-info/top_level.txt
pip_search_two-1.1.0.dist-info/RECORD
