Metadata-Version: 2.4
Name: pip-search-two
Version: 1.1.0
Summary: Search PyPI packages from the command-line by scraping the web interface
Author-email: "@readwithai" <talwrii@gmail.com>
License: MIT
Project-URL: Homepage, https://github.com/talwrii/pip-search-two
Project-URL: Repository, https://github.com/talwrii/pip-search-two
Project-URL: Issues, https://github.com/talwrii/pip-search-two/issues
Keywords: pip,pypi,search,packages,command-line
Classifier: Development Status :: 4 - Beta
Classifier: Intended Audience :: Developers
Classifier: License :: OSI Approved :: MIT License
Classifier: Operating System :: OS Independent
Classifier: Programming Language :: Python :: 3
Classifier: Programming Language :: Python :: 3.8
Classifier: Programming Language :: Python :: 3.9
Classifier: Programming Language :: Python :: 3.10
Classifier: Programming Language :: Python :: 3.11
Classifier: Programming Language :: Python :: 3.12
Classifier: Topic :: Software Development :: Libraries :: Python Modules
Classifier: Topic :: System :: Software Distribution
Requires-Python: >=3.8
License-File: LICENSE
Requires-Dist: requests>=2.25.0
Provides-Extra: dev
Requires-Dist: black; extra == "dev"
Requires-Dist: flake8; extra == "dev"
Requires-Dist: pytest; extra == "dev"
Requires-Dist: pytest-cov; extra == "dev"
Dynamic: license-file
